{
  "$schema": "https://json-schema.org/draft/2020-12/schema",
  "$id": "https://model.node.json",
  "title": "Node",
  "description": "This is the smallest unit of the whole history. It contains content: text.",
  "type": "object",
  "properties": {
    "nodeTitle": {
      "description": "The author's identifier for a node",
      "type": "string",
      "minLength": 2
    },
    "content": {
      "description": "For now, only text. Is it formatted text?",
      "type": "string"
    },
    "choices": {
      "description": "The set of possible choices for that particular node. From zero or more.",
      "type": "array",
      "items": {
        "$ref": "choice.json"
      },
      "minItems": 0,
      "uniqueItems": true
    }
  },
  "required": ["nodeId", "nodeName", "content", "choices"]
}